{
  "status": "issue19_foundation_closure_batches_not_final",
  "generated_by": "build_issue19_foundation_closure_batches.py",
  "source_foundation_release": "data/working/issue19-major-detail-foundation-release.csv",
  "output_major_batches": "data/working/issue19-foundation-closure-major-batches.csv",
  "output_page_index": "data/working/issue19-foundation-closure-page-index.csv",
  "output_school_index": "data/working/issue19-foundation-closure-school-index.csv",
  "major_row_count": 13736,
  "unique_major_line_id_count": 13736,
  "unique_batch_id_count": 13736,
  "page_index_row_count": 231,
  "school_index_row_count": 1100,
  "closure_batch_counts": {
    "C0-P0证据闭环先核": 5310,
    "C1-字段缺口先补": 7608,
    "C2-官网辅证交叉核验": 0,
    "C3-常规三方证据闭环": 609,
    "C4-低风险抽检但非最终": 209
  },
  "field_gap_field_counts": {
    "再选科目": 11456,
    "专业计划数": 6347,
    "学费": 1262
  },
  "p0_major_line_count": 5310,
  "field_gap_major_line_count": 12473,
  "b0_b1_diff_major_line_count": 854,
  "school_source_major_line_count": 854,
  "official_auxiliary_task_major_line_count": 854,
  "preference_major_line_count": 2499,
  "digital_media_major_line_count": 78,
  "computer_major_line_count": 1867,
  "teacher_major_line_count": 601,
  "final_available_count": 0,
  "final_major_list_candidate_count": 0,
  "next_stage_allowed_count": 0,
  "notes": [
    "主表仍是一行一个招生专业明细，页级/学校级索引只用于安排执行顺序。",
    "所有行仍保持非最终门禁；闭环批次只说明先核什么，不产生志愿排序结论。",
    "C2 主批次可能被 C0/C1 覆盖；含官网辅证任务专业明细数和 B0B1 官网差异专业明细数按动作维度单独统计。",
    "C0/C1 是当前数据底座阶段优先处理对象，湖北官方系统核验仍需登录态或最终志愿系统证据。"
  ]
}
